<?xml version="1.0" encoding="utf-8" standalone="yes"?>
<images>
  <image>
    <imageName>081.JPG</imageName>
    <resolution x="640" y="480" />
    <words>
      <word x="131" y="103" width="468" height="146">
        <character x="131" y="127" width="92" height="118" char="안" />
        <character x="232" y="129" width="93" height="116" char="경" />
        <character x="335" y="130" width="93" height="118" char="만" />
        <character x="435" y="133" width="75" height="116" char="들" />
        <character x="511" y="137" width="88" height="63" char="기" />
      </word>
      <word x="341" y="91" width="227" height="41">
        <character x="341" y="91" width="39" height="35" char="안" />
        <character x="382" y="92" width="36" height="34" char="경" />
        <character x="418" y="98" width="35" height="31" char="&amp;" />
        <character x="454" y="103" width="38" height="26" char="콘" />
        <character x="491" y="103" width="39" height="28" char="택" />
        <character x="531" y="103" width="37" height="29" char="트" />
      </word>
      <word x="101" y="250" width="358" height="48">
        <character x="101" y="252" width="29" height="43" char="T" />
        <character x="131" y="273" width="15" height="22" char="." />
        <character x="158" y="250" width="32" height="48" char="6" />
        <character x="190" y="250" width="50" height="44" char="7" />
        <character x="240" y="254" width="31" height="43" char="1" />
        <character x="274" y="265" width="18" height="18" char="-" />
        <character x="296" y="250" width="42" height="45" char="9" />
        <character x="340" y="257" width="38" height="40" char="1" />
        <character x="381" y="257" width="30" height="39" char="1" />
        <character x="413" y="255" width="46" height="38" char="9" />
      </word>
      <word x="495" y="255" width="142" height="39">
        <character x="495" y="255" width="40" height="39" char="영" />
        <character x="534" y="255" width="36" height="39" char="등" />
        <character x="570" y="256" width="36" height="36" char="포" />
        <character x="606" y="257" width="31" height="35" char="점" />
      </word>
    </words>
    <illumination>no</illumination>
    <difficulty>4</difficulty>
    <tag>
    </tag>
  </image>
</images>