<?xml version="1.0" encoding="utf-8" standalone="yes"?>
<images>
  <image>
    <imageName>image\0622\2007-12-09-day-exterior-037.jpg</imageName>
    <resolution x="1600" y="1200" />
    <words>
      <word x="621" y="935" width="87" height="266">
        <character x="622" y="935" width="86" height="123" char="술" />
        <character x="627" y="1066" width="28" height="46" char="마" />
        <character x="655" y="1064" width="23" height="50" char="시" />
        <character x="677" y="1066" width="20" height="47" char="는" />
        <character x="621" y="1122" width="78" height="79" char="노" />
      </word>
      <word x="615" y="838" width="111" height="91">
        <character x="615" y="839" width="57" height="87" char="귀" />
        <character x="672" y="838" width="54" height="91" char="궁" />
      </word>
      <word x="15" y="711" width="175" height="48">
        <character x="15" y="720" width="40" height="39" char="일" />
        <character x="54" y="716" width="34" height="38" char="반" />
        <character x="89" y="716" width="32" height="37" char="음" />
        <character x="120" y="711" width="32" height="44" char="식" />
        <character x="154" y="713" width="36" height="38" char="점" />
      </word>
      <word x="613" y="44" width="72" height="219">
        <character x="629" y="44" width="56" height="125" char="노" />
        <character x="613" y="132" width="72" height="131" char="래" />
      </word>
      <word x="612" y="232" width="91" height="164">
        <character x="612" y="232" width="40" height="114" char="주" />
        <character x="652" y="264" width="51" height="132" char="점" />
      </word>
      <word x="613" y="701" width="368" height="66">
        <character x="613" y="716" width="43" height="40" char="T" />
        <character x="661" y="709" width="38" height="47" char="8" />
        <character x="703" y="710" width="39" height="46" char="6" />
        <character x="739" y="707" width="41" height="43" char="2" />
        <character x="783" y="715" width="23" height="26" char="-" />
        <character x="809" y="704" width="34" height="46" char="9" />
        <character x="842" y="701" width="40" height="50" char="2" />
        <character x="885" y="706" width="37" height="44" char="2" />
        <character x="925" y="707" width="56" height="60" char="0" />
        <character x="647" y="736" width="17" height="19" char="." />
      </word>
      <word x="303" y="482" width="1105" height="234">
        <character x="303" y="536" width="130" height="180" char="술" />
        <character x="433" y="621" width="65" height="75" char="마" />
        <character x="497" y="618" width="60" height="73" char="시" />
        <character x="556" y="618" width="55" height="74" char="고" />
        <character x="615" y="541" width="94" height="151" char="노" />
        <character x="718" y="537" width="137" height="151" char="래" />
        <character x="866" y="599" width="76" height="74" char="하" />
        <character x="942" y="597" width="55" height="77" char="는" />
        <character x="1000" y="490" width="214" height="208" char="귀" />
        <character x="1218" y="482" width="190" height="218" char="궁" />
      </word>
    </words>
    <illumination>yes</illumination>
    <difficulty>4</difficulty>
    <tag>
    </tag>
  </image>
</images>