<?xml version="1.0" encoding="utf-8" standalone="yes"?>
<images>
  <image>
    <imageName>image\0623\2007-12-08-day-103.jpg</imageName>
    <resolution x="1600" y="1200" />
    <words>
      <word x="22" y="389" width="105" height="135">
        <character x="22" y="389" width="63" height="66" char="참" />
        <character x="53" y="457" width="33" height="44" char="이" />
        <character x="84" y="455" width="43" height="69" char="슬" />
      </word>
      <word x="517" y="606" width="254" height="57">
        <character x="517" y="606" width="40" height="43" char="S" />
        <character x="556" y="610" width="31" height="39" char="A" />
        <character x="588" y="608" width="40" height="46" char="M" />
        <character x="626" y="613" width="33" height="42" char="K" />
        <character x="658" y="618" width="33" height="42" char="A" />
        <character x="691" y="617" width="33" height="46" char="N" />
        <character x="726" y="622" width="45" height="41" char="G" />
      </word>
      <word x="496" y="483" width="276" height="143">
        <character x="496" y="483" width="142" height="129" char="롯" />
        <character x="640" y="494" width="132" height="132" char="데" />
      </word>
      <word x="792" y="4" width="59" height="73">
        <character x="784" y="4" width="59" height="73" char="림" />
      </word>
    </words>
    <illumination>no</illumination>
    <difficulty>1</difficulty>
    <tag>
    </tag>
  </image>
</images>