<?xml version="1.0" encoding="utf-8" standalone="yes"?>
<images>
  <image>
    <imageName>DSC03063.JPG</imageName>
    <resolution x="640" y="480" />
    <words>
      <word x="112" y="198" width="409" height="157">
        <character x="112" y="198" width="98" height="75" char="전" />
        <character x="224" y="203" width="97" height="77" char="민" />
        <character x="333" y="207" width="71" height="76" char="5" />
        <character x="416" y="215" width="105" height="76" char="길" />
      </word>
      <word x="140" y="277" width="351" height="78">
        <character x="140" y="277" width="39" height="51" char="J" />
        <character x="179" y="279" width="26" height="46" char="e" />
        <character x="205" y="287" width="30" height="39" char="o" />
        <character x="235" y="285" width="26" height="44" char="n" />
        <character x="261" y="290" width="37" height="44" char="m" />
        <character x="297" y="287" width="16" height="45" char="i" />
        <character x="314" y="290" width="21" height="46" char="n" />
        <character x="334" y="288" width="31" height="49" char="5" />
        <character x="380" y="295" width="29" height="47" char="o" />
        <character x="439" y="302" width="25" height="53" char="g" />
        <character x="463" y="294" width="14" height="49" char="i" />
        <character x="476" y="294" width="15" height="51" char="l" />
      </word>
    </words>
    <illumination>no</illumination>
    <difficulty>5</difficulty>
    <tag>
    </tag>
  </image>
</images>