<?xml version="1.0" encoding="utf-8" standalone="yes"?>
<images>
  <image>
    <imageName>DSC03718.JPG</imageName>
    <resolution x="640" y="480" />
    <words>
      <word x="132" y="0" width="242" height="63">
        <character x="132" y="0" width="61" height="63" char="발" />
        <character x="219" y="1" width="70" height="54" char="라" />
        <character x="308" y="0" width="66" height="55" char="드" />
      </word>
      <word x="111" y="74" width="291" height="60">
        <character x="111" y="74" width="52" height="60" char="헤" />
        <character x="173" y="74" width="49" height="58" char="어" />
        <character x="225" y="75" width="50" height="55" char="샵" />
        <character x="278" y="95" width="21" height="31" char="H" />
        <character x="299" y="98" width="13" height="30" char="a" />
        <character x="312" y="95" width="8" height="33" char="i" />
        <character x="320" y="97" width="15" height="32" char="r" />
        <character x="336" y="93" width="15" height="35" char="S" />
        <character x="353" y="94" width="15" height="35" char="h" />
        <character x="368" y="94" width="14" height="35" char="o" />
        <character x="382" y="95" width="20" height="34" char="p" />
      </word>
      <word x="29" y="248" width="221" height="45">
        <character x="29" y="252" width="14" height="37" char="T" />
        <character x="43" y="261" width="12" height="31" char="o" />
        <character x="52" y="252" width="14" height="37" char="t" />
        <character x="68" y="258" width="13" height="34" char="a" />
        <character x="82" y="258" width="7" height="31" char="l" />
        <character x="93" y="255" width="18" height="33" char="H" />
        <character x="112" y="264" width="17" height="27" char="a" />
        <character x="129" y="255" width="6" height="33" char="i" />
        <character x="135" y="260" width="8" height="28" char="r" />
        <character x="147" y="248" width="19" height="43" char="F" />
        <character x="166" y="259" width="17" height="34" char="a" />
        <character x="184" y="257" width="8" height="32" char="s" />
        <character x="192" y="256" width="17" height="33" char="h" />
        <character x="209" y="253" width="6" height="35" char="i" />
        <character x="215" y="262" width="15" height="23" char="o" />
        <character x="230" y="261" width="20" height="27" char="n" />
      </word>
      <word x="219" y="305" width="373" height="79">
        <character x="219" y="313" width="58" height="70" char="장" />
        <character x="273" y="310" width="53" height="74" char="민" />
        <character x="327" y="308" width="44" height="76" char="옥" />
        <character x="384" y="308" width="52" height="71" char="헤" />
        <character x="435" y="308" width="54" height="69" char="어" />
        <character x="491" y="307" width="50" height="75" char="라" />
        <character x="542" y="305" width="50" height="78" char="인" />
      </word>
      <word x="429" y="400" width="163" height="36">
        <character x="429" y="403" width="23" height="33" char="T" />
        <character x="457" y="406" width="18" height="27" char="4" />
        <character x="477" y="402" width="19" height="29" char="8" />
        <character x="496" y="401" width="13" height="31" char="4" />
        <character x="523" y="405" width="12" height="28" char="1" />
        <character x="535" y="405" width="17" height="31" char="5" />
        <character x="550" y="406" width="17" height="26" char="9" />
        <character x="568" y="400" width="24" height="35" char="7" />
      </word>
    </words>
    <illumination>no</illumination>
    <difficulty>2</difficulty>
    <tag>
    </tag>
  </image>
</images>