<?xml version="1.0" encoding="utf-8" standalone="yes"?>
<images>
  <image>
    <imageName>DSC02611.JPG</imageName>
    <resolution x="640" y="480" />
    <words>
      <word x="212" y="79" width="137" height="82">
        <character x="212" y="81" width="44" height="60" char="B" />
        <character x="258" y="79" width="55" height="62" char="A" />
        <character x="314" y="88" width="35" height="73" char="R" />
      </word>
      <word x="189" y="164" width="142" height="309">
        <character x="205" y="164" width="126" height="141" char="이" />
        <character x="189" y="310" width="142" height="163" char="공" />
      </word>
    </words>
    <illumination>no</illumination>
    <difficulty>2</difficulty>
    <tag>
    </tag>
  </image>
</images>